nemo_microservices/__init__.py
nemo_microservices/_base_client.py
nemo_microservices/_client.py
nemo_microservices/_compat.py
nemo_microservices/_constants.py
nemo_microservices/_exceptions.py
nemo_microservices/_files.py
nemo_microservices/_models.py
nemo_microservices/_qs.py
nemo_microservices/_resource.py
nemo_microservices/_response.py
nemo_microservices/_streaming.py
nemo_microservices/_types.py
nemo_microservices/_version.py
nemo_microservices/pagination.py
nemo_microservices/py.typed
nemo_microservices/_decoders/jsonl.py
nemo_microservices/_utils/__init__.py
nemo_microservices/_utils/_compat.py
nemo_microservices/_utils/_datetime_parse.py
nemo_microservices/_utils/_logs.py
nemo_microservices/_utils/_proxy.py
nemo_microservices/_utils/_reflection.py
nemo_microservices/_utils/_resources_proxy.py
nemo_microservices/_utils/_streams.py
nemo_microservices/_utils/_sync.py
nemo_microservices/_utils/_transform.py
nemo_microservices/_utils/_typing.py
nemo_microservices/_utils/_utils.py
nemo_microservices/beta/safe_synthesizer/__init__.py
nemo_microservices/beta/safe_synthesizer/defaults.py
nemo_microservices/beta/safe_synthesizer/errors.py
nemo_microservices/beta/safe_synthesizer/logging_utils.py
nemo_microservices/beta/safe_synthesizer/utils.py
nemo_microservices/beta/safe_synthesizer/config/__init__.py
nemo_microservices/beta/safe_synthesizer/config/autoconfig.py
nemo_microservices/beta/safe_synthesizer/config/base.py
nemo_microservices/beta/safe_synthesizer/config/data.py
nemo_microservices/beta/safe_synthesizer/config/differential_privacy.py
nemo_microservices/beta/safe_synthesizer/config/evaluate.py
nemo_microservices/beta/safe_synthesizer/config/external_results.py
nemo_microservices/beta/safe_synthesizer/config/generate.py
nemo_microservices/beta/safe_synthesizer/config/internal_results.py
nemo_microservices/beta/safe_synthesizer/config/job.py
nemo_microservices/beta/safe_synthesizer/config/parameters.py
nemo_microservices-1.5.0.dist-info/METADATA
nemo_microservices-1.5.0.dist-info/WHEEL
nemo_microservices-1.5.0.dist-info/licenses/LICENSE
nemo_microservices-1.5.0.dist-info/RECORD
