Metadata-Version: 2.3
Name: nemo-microservices
Version: 1.5.0
Summary: The official Python library for the NeMo Microservices API
Project-URL: Homepage, https://docs.nvidia.com/nemo/microservices/latest/about/index.html
Author: NVIDIA Corporation
License: Apache-2.0
Classifier: Intended Audience :: Developers
Classifier: License :: OSI Approved :: Apache Software License
Classifier: Operating System :: MacOS
Classifier: Operating System :: Microsoft :: Windows
Classifier: Operating System :: OS Independent
Classifier: Operating System :: POSIX
Classifier: Operating System :: POSIX :: Linux
Classifier: Programming Language :: Python :: 3.10
Classifier: Programming Language :: Python :: 3.11
Classifier: Programming Language :: Python :: 3.12
Classifier: Programming Language :: Python :: 3.13
Classifier: Programming Language :: Python :: 3.14
Classifier: Topic :: Software Development :: Libraries :: Python Modules
Classifier: Typing :: Typed
Requires-Python: >=3.10
Requires-Dist: anyio<5,>=3.5.0
Requires-Dist: distro<2,>=1.7.0
Requires-Dist: httpx<1,>=0.23.0
Requires-Dist: pydantic<3,>=1.9.0
Requires-Dist: sniffio
Requires-Dist: typing-extensions<5,>=4.10
Provides-Extra: aiohttp
Requires-Dist: aiohttp; extra == 'aiohttp'
Requires-Dist: httpx-aiohttp>=0.1.9; extra == 'aiohttp'
Provides-Extra: data-designer
Requires-Dist: huggingface-hub<1,>=0.34.4; extra == 'data-designer'
Requires-Dist: jinja2<4,>=3.1.6; extra == 'data-designer'
Requires-Dist: numpy>=1.23.5; extra == 'data-designer'
Requires-Dist: pandas>=1.5.3; extra == 'data-designer'
Requires-Dist: pyarrow>=19.0.1; extra == 'data-designer'
Requires-Dist: pydantic>=2.9.2; extra == 'data-designer'
Requires-Dist: pygments>=2.19.2; extra == 'data-designer'
Requires-Dist: python-json-logger==2.0.7; extra == 'data-designer'
Requires-Dist: pyyaml>=6.0.1; extra == 'data-designer'
Requires-Dist: requests<3,>=2.32.2; extra == 'data-designer'
Requires-Dist: rich>=13.7.1; extra == 'data-designer'
Provides-Extra: safe-synthesizer
Requires-Dist: datasets>=4.3.0; extra == 'safe-synthesizer'
Requires-Dist: faker>=20.0; extra == 'safe-synthesizer'
Requires-Dist: huggingface-hub<1,>=0.34.4; extra == 'safe-synthesizer'
Requires-Dist: jsonschema>=4.22.0; extra == 'safe-synthesizer'
Requires-Dist: pandas>=2.1.3; extra == 'safe-synthesizer'
Requires-Dist: pydantic-settings>=2.6.1; extra == 'safe-synthesizer'
Requires-Dist: pydantic[email]>=2.9.2; extra == 'safe-synthesizer'
Requires-Dist: python-json-logger==2.0.7; extra == 'safe-synthesizer'
Requires-Dist: pyyaml>=6.0.1; extra == 'safe-synthesizer'
Requires-Dist: rich; extra == 'safe-synthesizer'
Requires-Dist: structlog>=25.4.0; extra == 'safe-synthesizer'
Requires-Dist: tabulate>=0.8.10; extra == 'safe-synthesizer'
Requires-Dist: tqdm>=4.67.1; extra == 'safe-synthesizer'
